asyncserf/__init__.py
asyncserf/_version.py
asyncserf/client.py
asyncserf/codec.py
asyncserf/connection.py
asyncserf/environment_config.py
asyncserf/exceptions.py
asyncserf/result.py
asyncserf/stream.py
asyncserf/util.py
asyncserf-0.21.1.dist-info/LICENSE
asyncserf-0.21.1.dist-info/METADATA
asyncserf-0.21.1.dist-info/WHEEL
asyncserf-0.21.1.dist-info/top_level.txt
asyncserf-0.21.1.dist-info/RECORD
