Metadata-Version: 2.1
Name: asyncserf
Version: 0.21.1
Summary: Python client for the Serf orchestration tool
Home-page: https://github.com/smurfix/asyncserf
Author: Matthias Urlichs
Author-email: matthias@urlichs.de
Maintainer: Matthias Urlichs
Maintainer-email: matthias@urlichs.de
License: MIT
Keywords: Serf,orchestration,service discovery,anyio
Requires-Python: >=3.6
License-File: LICENSE
Requires-Dist: anyio (>=3)
Requires-Dist: attrs (>=18.1)
Requires-Dist: msgpack (>=0.5.0)
Requires-Dist: outcome
Requires-Dist: async-exit-stack ; python_version < '3.7'
Requires-Dist: async-generator ; python_version < '3.7'
